vit_tensorrt-0.1.0.dist-info/METADATA
vit_tensorrt-0.1.0.dist-info/WHEEL
vit_tensorrt-0.1.0.dist-info/entry_points.txt
vit_tensorrt-0.1.0.dist-info/licenses/LICENSE
vit_tensorrt/__init__.py
vit_tensorrt/analysis/__init__.py
vit_tensorrt/analysis/stats_calculator.py
vit_tensorrt/config/__init__.py
vit_tensorrt/config/attention_config.py
vit_tensorrt/config/encoder_config.py
vit_tensorrt/config/mlp_config.py
vit_tensorrt/config/train_config.py
vit_tensorrt/config/vit_config.py
vit_tensorrt/data/__init__.py
vit_tensorrt/data/vit_dataset.py
vit_tensorrt/data/vit_predict_image_transform.py
vit_tensorrt/data/vit_train_image_transform.py
vit_tensorrt/model/__init__.py
vit_tensorrt/model/encoder.py
vit_tensorrt/model/encoder_block.py
vit_tensorrt/model/mlp_block.py
vit_tensorrt/model/vit.py
vit_tensorrt/utils/__init__.py
vit_tensorrt/utils/meta_logger.py
vit_tensorrt-0.1.0.dist-info/RECORD
