Metadata-Version: 2.1
Name: ViT-TensorRT
Version: 0.1.0
Summary: A re-implementation of ViT containing utilities to convert to TensorRT engines and run in Triton.
Author-Email: KyleNewman97 <kyle@thenewmans.com.au>
License: MIT
Requires-Python: >=3.11
Requires-Dist: numpy>=2.1.1
Requires-Dist: pydantic>=2.9.1
Requires-Dist: torchvision>=0.19.1
Requires-Dist: scipy>=1.14.1
Requires-Dist: tqdm>=4.66.5
Requires-Dist: matplotlib>=3.9.2
Requires-Dist: tensorboard>=2.17.1
Requires-Dist: onnx>=1.17.0
Requires-Dist: torch>=2.4.1
Requires-Dist: nvidia-tensorrt>=99.0.0
Requires-Dist: pip>=24.2
Requires-Dist: tritonclient[http]>=2.46.0
Requires-Dist: tensorrt==10.4.0
